keter/__init__.py
keter/__main__.py
keter/chemistry.py
keter/data.py
keter/download.py
keter/forecasting.py
keter-0.0.1.dist-info/METADATA
keter-0.0.1.dist-info/WHEEL
keter-0.0.1.dist-info/entry_points.txt
keter-0.0.1.dist-info/top_level.txt
keter-0.0.1.dist-info/RECORD
