Metadata-Version: 2.1
Name: keter
Version: 0.0.1
Summary: Bioinformatics platform
Home-page: https://www.github.com/bnext-iqt/keter
Author: JJ Ben-Joseph
Author-email: jbenjoseph@iqt.org
License: Apache
Keywords: machine_learning artificial_intelligence medicine devops
Platform: UNKNOWN
Classifier: Topic :: Scientific/Engineering :: Artificial Intelligence
Classifier: Topic :: Scientific/Engineering :: Chemistry
Classifier: Topic :: Scientific/Engineering :: Medical Science Apps.
Classifier: Development Status :: 1 - Planning
Classifier: Intended Audience :: Developers
Classifier: Intended Audience :: Science/Research
Classifier: License :: OSI Approved :: Apache Software License
Classifier: Programming Language :: Python :: 3 :: Only
Classifier: Programming Language :: Python :: 3.8
Classifier: Operating System :: OS Independent
Requires-Python: >=3.6
Requires-Dist: rq
Requires-Dist: redis
